electrumx/__init__.py
electrumx_spesmilo-0.dist-info/LICENSE
electrumx_spesmilo-0.dist-info/METADATA
electrumx_spesmilo-0.dist-info/WHEEL
electrumx_spesmilo-0.dist-info/top_level.txt
electrumx_spesmilo-0.dist-info/RECORD
