Metadata-Version: 2.1
Name: electrumx-spesmilo
Version: 0
Summary: ElectrumX Server
Home-page: https://github.com/spesmilo/electrumx
Author: Electrum developers
Author-email: electrumdev@gmail.com
License: MIT Licence
Platform: UNKNOWN
Classifier: Development Status :: 1 - Planning
Classifier: License :: OSI Approved :: MIT License
Classifier: Operating System :: Unix
Classifier: Programming Language :: Python :: 3
